odoo/addons/mis_builder_budget_tier_validation/README.rst
odoo/addons/mis_builder_budget_tier_validation/__init__.py
odoo/addons/mis_builder_budget_tier_validation/__manifest__.py
odoo/addons/mis_builder_budget_tier_validation/i18n/mis_builder_budget_tier_validation.pot
odoo/addons/mis_builder_budget_tier_validation/models/__init__.py
odoo/addons/mis_builder_budget_tier_validation/models/mis_budget.py
odoo/addons/mis_builder_budget_tier_validation/models/tier_definition.py
odoo/addons/mis_builder_budget_tier_validation/readme/CONFIGURE.rst
odoo/addons/mis_builder_budget_tier_validation/readme/CONTRIBUTORS.rst
odoo/addons/mis_builder_budget_tier_validation/readme/DESCRIPTION.rst
odoo/addons/mis_builder_budget_tier_validation/readme/INSTALL.rst
odoo/addons/mis_builder_budget_tier_validation/readme/USAGE.rst
odoo/addons/mis_builder_budget_tier_validation/static/description/icon.png
odoo/addons/mis_builder_budget_tier_validation/static/description/index.html
odoo/addons/mis_builder_budget_tier_validation/tests/__init__.py
odoo/addons/mis_builder_budget_tier_validation/tests/common.py
odoo/addons/mis_builder_budget_tier_validation/tests/test_tier_validation.py
odoo/addons/mis_builder_budget_tier_validation/tests/tier_validation_tester.py
odoo/addons/mis_builder_budget_tier_validation/views/mis_budget_view.xml
odoo13_addon_mis_builder_budget_tier_validation-13.0.1.0.1.dev3.dist-info/METADATA
odoo13_addon_mis_builder_budget_tier_validation-13.0.1.0.1.dev3.dist-info/WHEEL
odoo13_addon_mis_builder_budget_tier_validation-13.0.1.0.1.dev3.dist-info/top_level.txt
odoo13_addon_mis_builder_budget_tier_validation-13.0.1.0.1.dev3.dist-info/RECORD
