Metadata-Version: 2.1
Name: odoo13-addon-mis-builder-budget-tier-validation
Version: 13.0.1.0.1.dev3
Summary: Extends the functionality of Mis Builder Budget to support a tier validation process.
Home-page: https://github.com/OCA/mis-builder/
Author: QubiQ 2010, Odoo Community Association (OCA)
Author-email: support@odoo-community.org
License: AGPL-3
Platform: UNKNOWN
Classifier: Programming Language :: Python
Classifier: Framework :: Odoo
Classifier: Framework :: Odoo :: 13.0
Classifier: License :: OSI Approved :: GNU Affero General Public License v3
Requires-Python: >=3.5
Requires-Dist: odoo13-addon-base-tier-validation
Requires-Dist: odoo13-addon-mis-builder-budget
Requires-Dist: odoo <13.1dev,>=13.0a
